<?xml version="1.0" encoding="UTF-8"?>
<beans xmlns="http://www.springframework.org/schema/beans"
	xmlns:xsi="http://www.w3.org/2001/XMLSchema-instance"
	xmlns:context="http://www.springframework.org/schema/context"
	xsi:schemaLocation="http://www.springframework.org/schema/beans 
    http://www.springframework.org/schema/beans/spring-beans.xsd 
    http://www.springframework.org/schema/context 
    http://www.springframework.org/schema/context/spring-context.xsd">

<!-- 	<bean id="employ" class="com.model.Employ" >
		<constructor-arg value="20"></constructor-arg>
		<constructor-arg value="two"></constructor-arg>
		
	</bean> -->
	
	<!-- <bean id="department" class="com.model.Department">
				
		<property name="deptId" value="123"> </property>
		<constructor-arg value="10"></constructor-arg>
	
	</bean>
  -->
  
  <bean id="department" class="com.model.Department">

		<property name="deptId" value="${d1}">
		</property>
		<property name="deptName" value="${d2}">
		</property>
		<property name="employ" ref="employ">
		</property>


	</bean>
</beans>